adafruit_avrprog.py
adafruit_circuitpython_avrprog-1.5.6.dist-info/licenses/LICENSE
adafruit_circuitpython_avrprog-1.5.6.dist-info/METADATA
adafruit_circuitpython_avrprog-1.5.6.dist-info/WHEEL
adafruit_circuitpython_avrprog-1.5.6.dist-info/top_level.txt
adafruit_circuitpython_avrprog-1.5.6.dist-info/RECORD
